haianh/__init__.py
haianh/hello.py
haianh-0.0.1.dist-info/LICENSE
haianh-0.0.1.dist-info/METADATA
haianh-0.0.1.dist-info/WHEEL
haianh-0.0.1.dist-info/top_level.txt
haianh-0.0.1.dist-info/RECORD
