Metadata-Version: 2.1
Name: haianh
Version: 0.0.1
Summary: Setting up a python package
Author: dohaianh
Author-email: haianhdo193@gmail.com
Keywords: python,test
License-File: LICENSE
